CHANGELOG.rst
LICENSE.rst
MANIFEST.in
README.rst
setup.py
clip/__init__.py
clip/core.py
clip/settings.py
clip.egg-info/PKG-INFO
clip.egg-info/SOURCES.txt
clip.egg-info/dependency_links.txt
clip.egg-info/top_level.txt
clip/bin/clip
clip/storage/__init__.py
clip/storage/base.py
clip/storage/json_store.py