Metadata-Version: 1.1
Name: clip
Version: 0.2.0
Summary: A CLI clipboard manager
Home-page: http://procrastinatingdev.com/clip/
Author: Adam McKerlie
Author-email: adammckerlie@gmail.com
License: Copyright (C) 2012 Adam McKerlie
